scsilicon2/__init__.py
scsilicon2/main.py
scsilicon2/random_tree.py
scsilicon2/utils.py
scsilicon2/version.py
SCSilicon2-1.0.1.dist-info/LICENSE
SCSilicon2-1.0.1.dist-info/METADATA
SCSilicon2-1.0.1.dist-info/WHEEL
SCSilicon2-1.0.1.dist-info/top_level.txt
SCSilicon2-1.0.1.dist-info/RECORD
