Metadata-Version: 2.1
Name: SCSilicon2
Version: 1.0.1
Summary: SCSilicon2: a single-cell genomics simulator which cost-effectively simulates single-cell genomics reads with haplotype-specific copy number annotation.
Home-page: https://github.com/xikanfeng2/SCSilicon2
Author: Xikang Feng
Author-email: Xikang Feng <fxk@nwpu.edu.cn>
Project-URL: Homepage, https://github.com/xikanfeng2/SCSilicon2
Project-URL: Issues, https://github.com/xikanfeng2/SCSilicon2/issues
Classifier: Programming Language :: Python :: 3
Classifier: License :: OSI Approved :: MIT License
Classifier: Operating System :: OS Independent
Requires-Python: >=3.6
License-File: LICENSE
Requires-Dist: pandas >=0.23.4
Requires-Dist: matplotlib >=3.0.2
Requires-Dist: networkx >=3.2.1
